oracle/__init__.py
oracle/oci_resource_search_mcp_server/__init__.py
oracle/oci_resource_search_mcp_server/models.py
oracle/oci_resource_search_mcp_server/server.py
oracle/oci_resource_search_mcp_server/tests/test_resource_search_tools.py
oracle_oci_resource_search_mcp_server-2.1.0.dist-info/METADATA
oracle_oci_resource_search_mcp_server-2.1.0.dist-info/WHEEL
oracle_oci_resource_search_mcp_server-2.1.0.dist-info/entry_points.txt
oracle_oci_resource_search_mcp_server-2.1.0.dist-info/licenses/LICENSE.txt
oracle_oci_resource_search_mcp_server-2.1.0.dist-info/RECORD
